virtualenv_here/__init__.py
virtualenv_here/main.py
virtualenv_here/tests/__init__.py
virtualenv_here-0.1.dist-info/DESCRIPTION.rst
virtualenv_here-0.1.dist-info/METADATA
virtualenv_here-0.1.dist-info/RECORD
virtualenv_here-0.1.dist-info/WHEEL
virtualenv_here-0.1.dist-info/entry_points.txt
virtualenv_here-0.1.dist-info/metadata.json
virtualenv_here-0.1.dist-info/top_level.txt
