Metadata-Version: 2.0
Name: virtualenv-here
Version: 0.1
Summary: Manage a virtualenv for a project based on the its path.
Home-page: https://github.com/nejucomo/virtualenv_here
Author: Nathan Wilcox
Author-email: nejucomo@gmail.com
License: MIT
Platform: UNKNOWN
